Metadata-Version: 2.1
Name: schema-transpose
Version: 0.1.0
Summary: A python library
License: MIT
License-File: LICENSE
Requires-Dist: pydantic
Requires-Dist: typer
Requires-Dist: jinja2
Requires-Dist: glom
Requires-Dist: py-markdown-table
Provides-Extra: dev
Requires-Dist: black ; extra == 'dev'
Requires-Dist: build ; extra == 'dev'
Requires-Dist: dapperdata ; extra == 'dev'
Requires-Dist: glom ; extra == 'dev'
Requires-Dist: isort ; extra == 'dev'
Requires-Dist: mypy ; extra == 'dev'
Requires-Dist: pip-tools ; extra == 'dev'
Requires-Dist: pytest ; extra == 'dev'
Requires-Dist: pytest-cov ; extra == 'dev'
Requires-Dist: pytest-pretty ; extra == 'dev'
Requires-Dist: versioneer ; extra == 'dev'
Requires-Dist: ruamel.yaml ; extra == 'dev'
